py2sqlite/__init__.py
py2sqlite/demo.py
py2sqlite/demo_classes.py
py2sqlite/py2sql.py
py2sqlite/util.py
py2sqlite_ehortl-0.0.5.dist-info/LICENSE
py2sqlite_ehortl-0.0.5.dist-info/LICENSE.txt
py2sqlite_ehortl-0.0.5.dist-info/METADATA
py2sqlite_ehortl-0.0.5.dist-info/WHEEL
py2sqlite_ehortl-0.0.5.dist-info/top_level.txt
py2sqlite_ehortl-0.0.5.dist-info/RECORD
