Metadata-Version: 2.1
Name: py2sqlite-ehortl
Version: 0.0.5
Summary: Package to work with SQLite
Home-page: https://github.com/ehorTL/py2sqlite
Author: Yaroslav Haidai, Yehor Polishchuk
Author-email: e-dp@ukr.net
License: mit
Keywords: py2sqlite,SQLite,Py2SQL,SQL
Platform: UNKNOWN
Classifier: Intended Audience :: Developers
Classifier: Topic :: Software Development :: Build Tools
Classifier: License :: OSI Approved :: MIT License
Classifier: Programming Language :: Python :: 3
